flask_fluentd_event/__init__.py
flask_fluentd_event-0.1.0.dist-info/AUTHORS.rst
flask_fluentd_event-0.1.0.dist-info/LICENSE
flask_fluentd_event-0.1.0.dist-info/METADATA
flask_fluentd_event-0.1.0.dist-info/WHEEL
flask_fluentd_event-0.1.0.dist-info/top_level.txt
flask_fluentd_event-0.1.0.dist-info/RECORD
