Metadata-Version: 2.1
Name: flask-fluentd-event
Version: 0.1.0
Summary: Flask plugin to handle event with fluentd.
Home-page: https://github.com/yoophi/flask_fluentd_event
Author: Pyunghyuk Yoo
Author-email: yoophi@gmail.com
License: MIT license
Keywords: flask_fluentd_event
Platform: UNKNOWN
Classifier: Development Status :: 2 - Pre-Alpha
Classifier: Intended Audience :: Developers
Classifier: License :: OSI Approved :: MIT License
Classifier: Natural Language :: English
Classifier: Programming Language :: Python :: 3
Classifier: Programming Language :: Python :: 3.5
Classifier: Programming Language :: Python :: 3.6
Classifier: Programming Language :: Python :: 3.7
Classifier: Programming Language :: Python :: 3.8
Requires-Python: >=3.5
Requires-Dist: fluent-logger
Requires-Dist: six
